odoo9_addon_mrp_bom_structure_report_level_1-9.0.1.0.0.99.dev7-nspkg.pth
odoo_addons/mrp_bom_structure_report_level_1/README.rst
odoo_addons/mrp_bom_structure_report_level_1/__init__.py
odoo_addons/mrp_bom_structure_report_level_1/__openerp__.py
odoo_addons/mrp_bom_structure_report_level_1/i18n/de.po
odoo_addons/mrp_bom_structure_report_level_1/i18n/fr.po
odoo_addons/mrp_bom_structure_report_level_1/i18n/mrp_bom_structure_report_level_1.pot
odoo_addons/mrp_bom_structure_report_level_1/report/__init__.py
odoo_addons/mrp_bom_structure_report_level_1/report/bom_structure.py
odoo_addons/mrp_bom_structure_report_level_1/static/description/icon.png
odoo_addons/mrp_bom_structure_report_level_1/static/description/index.html
odoo_addons/mrp_bom_structure_report_level_1/views/mrp_bom_view.xml
odoo_addons/mrp_bom_structure_report_level_1/views/report_mrpbomstructure.xml
odoo9_addon_mrp_bom_structure_report_level_1-9.0.1.0.0.99.dev7.dist-info/METADATA
odoo9_addon_mrp_bom_structure_report_level_1-9.0.1.0.0.99.dev7.dist-info/WHEEL
odoo9_addon_mrp_bom_structure_report_level_1-9.0.1.0.0.99.dev7.dist-info/namespace_packages.txt
odoo9_addon_mrp_bom_structure_report_level_1-9.0.1.0.0.99.dev7.dist-info/top_level.txt
odoo9_addon_mrp_bom_structure_report_level_1-9.0.1.0.0.99.dev7.dist-info/RECORD
