Metadata-Version: 2.1
Name: odoo9-addon-mrp-bom-structure-report-level-1
Version: 9.0.1.0.0.99.dev7
Summary: MRP BOM Structure Report Level 1
Home-page: https://github.com/OCA/manufacture-reporting
Author: Eficent, Odoo Community Association (OCA)
Author-email: support@odoo-community.org
License: AGPL-3
Platform: UNKNOWN
Classifier: Programming Language :: Python
Classifier: Framework :: Odoo
Classifier: License :: OSI Approved :: GNU Affero General Public License v3
Requires-Python: ~=2.7
Requires-Dist: odoo (<9.1a,>=9.0a)
